pytermtables/__init__.py
pytermtables/pytermtables.py
pytermtables-1.0.31.dist-info/LICENSE.txt
pytermtables-1.0.31.dist-info/METADATA
pytermtables-1.0.31.dist-info/WHEEL
pytermtables-1.0.31.dist-info/top_level.txt
pytermtables-1.0.31.dist-info/RECORD
