Metadata-Version: 2.1
Name: pytermtables
Version: 1.0.31
Summary: CSV Python tables in terminal
Home-page: https://github.com/Spacerulerwill/pytermtables
Author: William Redding
Author-email: williamdredding@gmail.com
License: zlib/libpng
Keywords: csv
Classifier: Development Status :: 5 - Production/Stable
Classifier: Operating System :: Microsoft :: Windows :: Windows 10
Classifier: License :: OSI Approved :: zlib/libpng License
Classifier: Programming Language :: Python :: 3
License-File: LICENSE.txt
